mail2mongo/__init__.py
mail2mongo-0.3.3.dist-info/entry_points.txt
mail2mongo-0.3.3.dist-info/LICENSE
mail2mongo-0.3.3.dist-info/WHEEL
mail2mongo-0.3.3.dist-info/METADATA
mail2mongo-0.3.3.dist-info/RECORD
