Metadata-Version: 2.1
Name: mail2mongo
Version: 0.3.3
Summary: Simple SMTP daemon which save incoming emails to MongoDB
Home-page: https://github.com/inn0kenty/mail2mongo
License: UNKNOWN
Author: Innokenty Lebedev
Author-email: innlebedev@protonmail.com
Requires-Python: >=3.5
Classifier: License :: OSI Approved :: MIT License
Classifier: Programming Language :: Python :: 3.5
Classifier: Programming Language :: Python :: 3.6
Requires-Dist: aiohttp>=3.1.3,<4
Requires-Dist: aiosmtpd>=1.1,<2
Requires-Dist: cchardet>=2.1.1,<3
Requires-Dist: motor>=1.2.1,<2
